saltext/elasticsearch/__init__.py
saltext/elasticsearch/loader.py
saltext/elasticsearch/version.py
saltext/elasticsearch/modules/__init__.py
saltext/elasticsearch/modules/elasticsearch6_mod.py
saltext/elasticsearch/modules/elasticsearch8_mod.py
saltext/elasticsearch/returners/__init__.py
saltext/elasticsearch/returners/elasticsearch6_mod.py
saltext/elasticsearch/returners/elasticsearch8_mod.py
saltext/elasticsearch/states/__init__.py
saltext/elasticsearch/states/elasticsearch_mod.py
saltext.elasticsearch-1.2.1.dist-info/LICENSE
saltext.elasticsearch-1.2.1.dist-info/METADATA
saltext.elasticsearch-1.2.1.dist-info/WHEEL
saltext.elasticsearch-1.2.1.dist-info/entry_points.txt
saltext.elasticsearch-1.2.1.dist-info/top_level.txt
saltext.elasticsearch-1.2.1.dist-info/RECORD
