Metadata-Version: 2.1
Name: saltext.elasticsearch
Version: 1.2.1
Summary: 'Elasticsearch extension'
Home-page: http://github.com/cesan3/salt-ext-elasticsearch
Author: Cesar Sanchez
Author-email: cesan3@gmail.com
License: Apache Software License
Project-URL: Source, http://github.com/cesan3/salt-ext-elasticsearch
Project-URL: Tracker, http://github.com/cesan3/salt-ext-elasticsearch/issues
Keywords: salt-extension
Platform: any
Classifier: Programming Language :: Python
Classifier: Programming Language :: Cython
Classifier: Programming Language :: Python :: 3
Classifier: Programming Language :: Python :: 3 :: Only
Classifier: Programming Language :: Python :: 3.6
Classifier: Programming Language :: Python :: 3.7
Classifier: Programming Language :: Python :: 3.8
Classifier: Programming Language :: Python :: 3.9
Classifier: Development Status :: 4 - Beta
Classifier: Intended Audience :: Developers
Classifier: License :: OSI Approved :: Apache Software License
Requires-Python: >=3.5
License-File: LICENSE
Requires-Dist: salt >=3004.1
Provides-Extra: dev
Requires-Dist: nox ==2021.6.12 ; extra == 'dev'
Requires-Dist: pre-commit ==2.13.0 ; extra == 'dev'
Requires-Dist: pylint ; extra == 'dev'
Requires-Dist: SaltPyLint ; extra == 'dev'
Provides-Extra: docs
Requires-Dist: furo ; extra == 'docs'
Requires-Dist: enchant ; extra == 'docs'
Requires-Dist: sphinx ; extra == 'docs'
Requires-Dist: sphinx-copybutton ; extra == 'docs'
Requires-Dist: sphinx-prompt ; extra == 'docs'
Requires-Dist: sphinxcontrib-spelling ; extra == 'docs'
Requires-Dist: requests ; extra == 'docs'
Provides-Extra: docsauto
Requires-Dist: sphinx-autobuild ; extra == 'docsauto'
Provides-Extra: tests
Requires-Dist: mock >=3.0.0 ; extra == 'tests'
Requires-Dist: docker ; extra == 'tests'
Requires-Dist: pytest >=7.2.0 ; extra == 'tests'
Requires-Dist: pytest-salt-factories >=1.0.0rc27 ; extra == 'tests'
Requires-Dist: pytest-helpers-namespace >=2019.1.8 ; extra == 'tests'
Requires-Dist: pytest-subtests ; extra == 'tests'
Requires-Dist: pytest-timeout ; extra == 'tests'
Requires-Dist: pytest-httpserver ; extra == 'tests'
Requires-Dist: pytest-custom-exit-code >=0.3 ; extra == 'tests'
Requires-Dist: flaky ; extra == 'tests'
Requires-Dist: more-itertools ; extra == 'tests'
